CHANGELOG.rst
MANIFEST.in
README.rst
TODO.txt
VERSION.txt
example.ini
setup.cfg
setup.py
doc/access.rst
doc/example.html
doc/example.json
doc/example.pdf
doc/example.rst
doc/example.txt
doc/example.txt.asc
doc/example.wadl
doc/example.xml
doc/example.yaml
doc/typeregistry.rst
pyramid_describe/__init__.py
pyramid_describe/access.py
pyramid_describe/cli.py
pyramid_describe/constant.py
pyramid_describe/controller.py
pyramid_describe/describer.py
pyramid_describe/doctree.py
pyramid_describe/entry.py
pyramid_describe/i18n.py
pyramid_describe/integration.py
pyramid_describe/isstr.py
pyramid_describe/params.py
pyramid_describe/render.py
pyramid_describe/reparse.py
pyramid_describe/resolve.py
pyramid_describe/rst.py
pyramid_describe/scope.py
pyramid_describe/test_access.py
pyramid_describe/test_constant.py
pyramid_describe/test_describe.py
pyramid_describe/test_example.py
pyramid_describe/test_helpers.py
pyramid_describe/test_params.py
pyramid_describe/test_render.py
pyramid_describe/test_typereg.py
pyramid_describe/typereg.py
pyramid_describe/util.py
pyramid_describe.egg-info/PKG-INFO
pyramid_describe.egg-info/SOURCES.txt
pyramid_describe.egg-info/dependency_links.txt
pyramid_describe.egg-info/entry_points.txt
pyramid_describe.egg-info/requires.txt
pyramid_describe.egg-info/top_level.txt
pyramid_describe.egg-info/zip-safe
pyramid_describe/renderer/__init__.py
pyramid_describe/renderer/test_wadl.py
pyramid_describe/renderer/wadl.py
pyramid_describe/renderer/xml.py
pyramid_describe/syntax/__init__.py
pyramid_describe/syntax/docorator.py
pyramid_describe/syntax/docref.py
pyramid_describe/syntax/test_docorator.py
pyramid_describe/syntax/test_docref.py
pyramid_describe/syntax/test_title.py
pyramid_describe/syntax/title.py
pyramid_describe/syntax/numpydoc/__init__.py
pyramid_describe/syntax/numpydoc/extractor.py
pyramid_describe/syntax/numpydoc/merger.py
pyramid_describe/syntax/numpydoc/parser.py
pyramid_describe/syntax/numpydoc/plugin.py
pyramid_describe/syntax/numpydoc/test.py
pyramid_describe/syntax/numpydoc/test_extractor.py
pyramid_describe/syntax/numpydoc/test_parser.py
pyramid_describe/template/render.mako
pyramid_describe/template/rst2html.css
pyramid_describe/template/txt.mako
pyramid_describe/test/__init__.py
