Metadata-Version: 1.1
Name: pyramid-describe
Version: 0.5.2
Summary: A pyramid plugin that describes a pyramid application URL hierarchy via inspection.
Home-page: http://github.com/cadithealth/pyramid_describe
Author: Philip J Grabner, Cadit Health Inc
Author-email: oss@cadit.com
License: MIT (http://opensource.org/licenses/MIT)
Keywords: pyramid application url inspection reflection description describe
Platform: any
Classifier: Development Status :: 4 - Beta
Classifier: Intended Audience :: Developers
Classifier: Programming Language :: Python
Classifier: Operating System :: OS Independent
Classifier: Natural Language :: English
Classifier: License :: OSI Approved :: MIT License
Classifier: License :: Public Domain
